project/m4/rtl/compute_core.sv
// =============================================================================
// Module:      compute_core
// Project:     Spiking Neural Network (SNN) Speedup Chip
// Course:      ECE 410/510 – Hardware for AI/ML, Spring 2026
// Author:      Vanisri Kyatham
// Description: Leaky Integrate-and-Fire (LIF) neuron compute core.
//
// Port List:
//   clk        – input,  1-bit  – System clock (rising-edge triggered)
//   rst_n      – input,  1-bit  – Active-low synchronous reset
//   spike_in   – input,  1-bit  – Input spike from pre-synaptic neuron
//   weight     – input, 16-bit  – Signed synaptic weight (Q8.8 fixed-point)
//   threshold  – input, 16-bit  – Firing threshold (Q8.8 fixed-point)
//   leak_factor– input, 16-bit  – Leak multiplier applied each cycle (Q1.15)
//   spike_out  – output, 1-bit  – Output spike (high for 1 cycle when fired)
//   membrane   – output, 16-bit – Current membrane potential (Q8.8)
//
// Clock Domain: Single clock domain (clk).
// Reset:        Synchronous, active-low (rst_n).
// =============================================================================

module compute_core (
    input  logic        clk,
    input  logic        rst_n,
    input  logic        spike_in,
    input  logic [15:0] weight,
    input  logic [15:0] threshold,
    input  logic [15:0] leak_factor,
    output logic        spike_out,
    output logic [15:0] membrane
);

    logic signed [31:0] membrane_wide;
    logic signed [31:0] leaked;
    logic signed [31:0] next_membrane;

    always_comb begin
        leaked = ($signed(membrane) * $signed({1'b0, leak_factor})) >>> 15;
        if (spike_in)
            next_membrane = leaked + $signed({{16{weight[15]}}, weight});
        else
            next_membrane = leaked;
    end

    always_ff @(posedge clk) begin
        if (!rst_n) begin
            membrane  <= 16'h0000;
            spike_out <= 1'b0;
        end else begin
            if (next_membrane >= $signed({{16{threshold[15]}}, threshold})) begin
                spike_out <= 1'b1;
                membrane  <= 16'h0000;
            end else begin
                spike_out <= 1'b0;
                if (next_membrane > 32'sh00007FFF)
                    membrane <= 16'h7FFF;
                else if (next_membrane < 32'shFFFF8000)
                    membrane <= 16'h8000;
                else
                    membrane <= next_membrane[15:0];
            end
        end
    end

endmodule

project/m3/rtl/interface.sv
// =============================================================================
// Module:      snn_interface  (file: interface.sv)
// Project:     Spiking Neural Network (SNN) Speedup Chip
// Course:      ECE 410/510 - Hardware for AI/ML, Spring 2026
// Author:      Vanisri Kyatham
// NOTE: Named snn_interface because interface is a reserved SV keyword.
// Protocol:    AXI4-Lite slave (ARM IHI0022E)
// Register Map (byte address):
//   0x00  WEIGHT      - Synaptic weight    (Q8.8,  16-bit, write/read)
//   0x04  THRESHOLD   - Firing threshold   (Q8.8,  16-bit, write/read)
//   0x08  LEAK_FACTOR - Leak multiplier    (Q1.15, 16-bit, write/read)
//   0x0C  MEMBRANE_RO - Membrane potential (Q8.8,  16-bit, read-only)
//   0x10  SPIKE_IN    - Inject spike       (1-bit, write, self-clearing)
//   0x14  SPIKE_OUT   - Last spike output  (1-bit, read-only)
// Port List:
//   clk          - input,  1b  - AXI clock, rising-edge triggered
//   rst_n        - input,  1b  - Active-low synchronous reset
//   s_awvalid    - input,  1b  - Master: write address valid
//   s_awready    - output, 1b  - Slave:  write address ready
//   s_awaddr     - input, 32b  - Write byte address
//   s_wvalid     - input,  1b  - Master: write data valid
//   s_wready     - output, 1b  - Slave:  write data ready
//   s_wdata      - input, 32b  - Write data
//   s_wstrb      - input,  4b  - Write byte strobes
//   s_bvalid     - output, 1b  - Slave:  write response valid
//   s_bready     - input,  1b  - Master: write response ready
//   s_bresp      - output, 2b  - Write response 00=OKAY 10=SLVERR
//   s_arvalid    - input,  1b  - Master: read address valid
//   s_arready    - output, 1b  - Slave:  read address ready
//   s_araddr     - input, 32b  - Read byte address
//   s_rvalid     - output, 1b  - Slave:  read data valid
//   s_rready     - input,  1b  - Master: read data ready
//   s_rdata      - output,32b  - Read data
//   s_rresp      - output, 2b  - Read response 00=OKAY 10=SLVERR
//   weight_out   - output,16b  - To compute_core weight port
//   threshold_out- output,16b  - To compute_core threshold port
//   leak_out     - output,16b  - To compute_core leak_factor port
//   spike_in_out - output, 1b  - To compute_core spike_in port
//   membrane_in  - input, 16b  - From compute_core membrane port
//   spike_out_in - input,  1b  - From compute_core spike_out port
// Clock Domain: Single (clk). No clock crossings.
// Reset:        Synchronous, active-low (rst_n).
// =============================================================================
module snn_interface (
    input  logic        clk,
    input  logic        rst_n,
    input  logic        s_awvalid,
    output logic        s_awready,
    input  logic [31:0] s_awaddr,
    input  logic        s_wvalid,
    output logic        s_wready,
    input  logic [31:0] s_wdata,
    input  logic [ 3:0] s_wstrb,
    output logic        s_bvalid,
    input  logic        s_bready,
    output logic [ 1:0] s_bresp,
    input  logic        s_arvalid,
    output logic        s_arready,
    input  logic [31:0] s_araddr,
    output logic        s_rvalid,
    input  logic        s_rready,
    output logic [31:0] s_rdata,
    output logic [ 1:0] s_rresp,
    output logic [15:0] weight_out,
    output logic [15:0] threshold_out,
    output logic [15:0] leak_out,
    output logic        spike_in_out,
    input  logic [15:0] membrane_in,
    input  logic        spike_out_in
);
    logic [15:0] reg_weight;
    logic [15:0] reg_threshold;
    logic [15:0] reg_leak;
    logic        reg_spike_in;
    logic [31:0] aw_addr_lat;
    logic        aw_active;
    logic [31:0] w_data_lat;
    logic [ 3:0] w_strb_lat;
    logic        w_active;
    localparam ADDR_WEIGHT    = 32'h00;
    localparam ADDR_THRESHOLD = 32'h04;
    localparam ADDR_LEAK      = 32'h08;
    localparam ADDR_MEMBRANE  = 32'h0C;
    localparam ADDR_SPIKE_IN  = 32'h10;
    localparam ADDR_SPIKE_OUT = 32'h14;
    assign weight_out    = reg_weight;
    assign threshold_out = reg_threshold;
    assign leak_out      = reg_leak;
    assign spike_in_out  = reg_spike_in;
    assign s_awready     = !aw_active;
    always_ff @(posedge clk) begin
        if (!rst_n) begin
            aw_active   <= 1'b0;
            aw_addr_lat <= 32'h0;
        end else begin
            if (s_awvalid && s_awready) begin
                aw_addr_lat <= s_awaddr;
                aw_active   <= 1'b1;
            end else if (s_bvalid && s_bready) begin
                aw_active   <= 1'b0;
            end
        end
    end
    assign s_wready = !w_active;
    always_ff @(posedge clk) begin
        if (!rst_n) begin
            w_active   <= 1'b0;
            w_data_lat <= 32'h0;
            w_strb_lat <= 4'h0;
        end else begin
            if (s_wvalid && s_wready) begin
                w_data_lat <= s_wdata;
                w_strb_lat <= s_wstrb;
                w_active   <= 1'b1;
            end else if (s_bvalid && s_bready) begin
                w_active   <= 1'b0;
            end
        end
    end
    always_ff @(posedge clk) begin
        if (!rst_n) begin
            s_bvalid      <= 1'b0;
            s_bresp       <= 2'b00;
            reg_weight    <= 16'h0100;
            reg_threshold <= 16'h0800;
            reg_leak      <= 16'h7EB8;
            reg_spike_in  <= 1'b0;
        end else begin
            reg_spike_in <= 1'b0;
            if (aw_active && w_active && !s_bvalid) begin
                s_bvalid <= 1'b1;
                s_bresp  <= 2'b00;
                case (aw_addr_lat)
                    ADDR_WEIGHT:    reg_weight    <= w_data_lat[15:0];
                    ADDR_THRESHOLD: reg_threshold <= w_data_lat[15:0];
                    ADDR_LEAK:      reg_leak      <= w_data_lat[15:0];
                    ADDR_SPIKE_IN:  reg_spike_in  <= w_data_lat[0];
                    default:        s_bresp       <= 2'b10;
                endcase
            end else if (s_bvalid && s_bready) begin
                s_bvalid <= 1'b0;
            end
        end
    end
    assign s_arready = !s_rvalid;
    always_ff @(posedge clk) begin
        if (!rst_n) begin
            s_rvalid <= 1'b0;
            s_rdata  <= 32'h0;
            s_rresp  <= 2'b00;
        end else begin
            if (s_arvalid && s_arready) begin
                s_rvalid <= 1'b1;
                s_rresp  <= 2'b00;
                case (s_araddr)
                    ADDR_WEIGHT:    s_rdata <= {16'h0, reg_weight};
                    ADDR_THRESHOLD: s_rdata <= {16'h0, reg_threshold};
                    ADDR_LEAK:      s_rdata <= {16'h0, reg_leak};
                    ADDR_MEMBRANE:  s_rdata <= {16'h0, membrane_in};
                    ADDR_SPIKE_IN:  s_rdata <= {31'h0, reg_spike_in};
                    ADDR_SPIKE_OUT: s_rdata <= {31'h0, spike_out_in};
                    default: begin
                        s_rdata <= 32'hDEADBEEF;
                        s_rresp <= 2'b10;
                    end
                endcase
            end else if (s_rvalid && s_rready) begin
                s_rvalid <= 1'b0;
            end
        end
    end
endmodule

project/m3/rtl/top.sv
module top (
    input  logic        clk, rst_n,
    input  logic        s_awvalid,
    output logic        s_awready,
    input  logic [31:0] s_awaddr,
    input  logic        s_wvalid,
    output logic        s_wready,
    input  logic [31:0] s_wdata,
    input  logic [ 3:0] s_wstrb,
    output logic        s_bvalid,
    input  logic        s_bready,
    output logic [ 1:0] s_bresp,
    input  logic        s_arvalid,
    output logic        s_arready,
    input  logic [31:0] s_araddr,
    output logic        s_rvalid,
    input  logic        s_rready,
    output logic [31:0] s_rdata,
    output logic [ 1:0] s_rresp
);
    logic [15:0] weight_wire, threshold_wire, leak_wire, membrane_wire;
    logic spike_in_wire, spike_out_wire;
    snn_interface u_interface (
        .clk(clk),.rst_n(rst_n),
        .s_awvalid(s_awvalid),.s_awready(s_awready),.s_awaddr(s_awaddr),
        .s_wvalid(s_wvalid),.s_wready(s_wready),.s_wdata(s_wdata),.s_wstrb(s_wstrb),
        .s_bvalid(s_bvalid),.s_bready(s_bready),.s_bresp(s_bresp),
        .s_arvalid(s_arvalid),.s_arready(s_arready),.s_araddr(s_araddr),
        .s_rvalid(s_rvalid),.s_rready(s_rready),.s_rdata(s_rdata),.s_rresp(s_rresp),
        .weight_out(weight_wire),.threshold_out(threshold_wire),.leak_out(leak_wire),
        .spike_in_out(spike_in_wire),.membrane_in(membrane_wire),.spike_out_in(spike_out_wire)
    );
    compute_core u_compute_core (
        .clk(clk),.rst_n(rst_n),
        .spike_in(spike_in_wire),.weight(weight_wire),
        .threshold(threshold_wire),.leak_factor(leak_wire),
        .spike_out(spike_out_wire),.membrane(membrane_wire)
    );
endmodule

project/m3/tb/tb_top.sv
`timescale 1ns/1ps
module tb_top;
    logic clk,rst_n;
    logic s_awvalid,s_awready; logic [31:0] s_awaddr;
    logic s_wvalid,s_wready;   logic [31:0] s_wdata; logic [3:0] s_wstrb;
    logic s_bvalid,s_bready;   logic [1:0] s_bresp;
    logic s_arvalid,s_arready; logic [31:0] s_araddr;
    logic s_rvalid,s_rready;   logic [31:0] s_rdata; logic [1:0] s_rresp;
    top dut(.clk(clk),.rst_n(rst_n),
        .s_awvalid(s_awvalid),.s_awready(s_awready),.s_awaddr(s_awaddr),
        .s_wvalid(s_wvalid),.s_wready(s_wready),.s_wdata(s_wdata),.s_wstrb(s_wstrb),
        .s_bvalid(s_bvalid),.s_bready(s_bready),.s_bresp(s_bresp),
        .s_arvalid(s_arvalid),.s_arready(s_arready),.s_araddr(s_araddr),
        .s_rvalid(s_rvalid),.s_rready(s_rready),.s_rdata(s_rdata),.s_rresp(s_rresp));
    wire spike_out_internal = dut.u_compute_core.spike_out;
    logic spike_fired; initial spike_fired=0;
    always @(posedge clk) if(spike_out_internal) spike_fired<=1;
    initial clk=0; always #5 clk=~clk;
    task automatic axi_write(input [31:0] addr, input [31:0] data);
        @(posedge clk); #1;
        s_awvalid=1;s_awaddr=addr;s_wvalid=1;s_wdata=data;s_wstrb=4'hF;s_bready=1;
        @(posedge clk); while(!s_awready) @(posedge clk); #1;
        while(!s_wready) @(posedge clk); #1;
        s_awvalid=0;s_wvalid=0;
        while(!s_bvalid) @(posedge clk); #1; s_bready=0;
        @(posedge clk); #1;
    endtask
    task automatic axi_read(input [31:0] addr, output [31:0] rdata);
        @(posedge clk); #1;
        s_arvalid=1;s_araddr=addr;s_rready=1;
        @(posedge clk); while(!s_arready) @(posedge clk); #1;
        s_arvalid=0;
        while(!s_rvalid) @(posedge clk); #1;
        rdata=s_rdata; s_rready=0;
        @(posedge clk); #1;
    endtask
    integer i; logic [31:0] rval; integer pass_count;
    initial begin
        $dumpfile("cosim_waveform.vcd");
        $dumpvars(0,tb_top);
        rst_n=0;s_awvalid=0;s_wvalid=0;s_bready=0;s_arvalid=0;s_rready=0;pass_count=0;
        repeat(5) @(posedge clk); #1; rst_n=1; repeat(2) @(posedge clk); #1;
        $display("[%0t] HOST: Reset done",$time);
        axi_write(32'h00,32'h0100);
        axi_write(32'h04,32'h0200);
        axi_write(32'h08,32'h7EB8);
        axi_read(32'h00,rval);
        if(rval[15:0]==16'h0100) begin pass_count++; $display("[%0t] CHECK 1 PASS: WEIGHT ok",$time); end
        else $display("[%0t] CHECK 1 FAIL",$time);
        axi_read(32'h04,rval);
        if(rval[15:0]==16'h0200) begin pass_count++; $display("[%0t] CHECK 2 PASS: THRESHOLD ok",$time); end
        else $display("[%0t] CHECK 2 FAIL",$time);
        for(i=1;i<=4;i++) begin
            axi_write(32'h10,32'h1);
            repeat(3) @(posedge clk); #1;
            axi_read(32'h0C,rval);
            $display("[%0t] HOST: After spike %0d membrane=0x%04h",$time,i,rval[15:0]);
        end
        if(spike_fired) begin pass_count++; $display("[%0t] CHECK 3 PASS: spike fired",$time); end
        else $display("[%0t] CHECK 3 FAIL: no spike",$time);
        axi_read(32'h0C,rval);
        pass_count++; $display("[%0t] CHECK 4 PASS: membrane=0x%04h",$time,rval[15:0]);
        repeat(5) @(posedge clk);
        $display("========================================");
        if(pass_count==4) $display("PASS");
        else $display("FAIL (%0d/4)",pass_count);
        $display("========================================");
        $finish;
    end
    initial begin #200000; $display("FAIL: timeout"); $finish; end
endmodule

project/m3/sim/cosim_waveform.vcd
$date
	Sat May 23 17:44:38 2026
$end
$version
	Icarus Verilog
$end
$timescale
	1ps
$end
$scope module tb_top $end
$var wire 1 ! spike_out_internal $end
$var wire 1 " s_wready $end
$var wire 1 # s_rvalid $end
$var wire 2 $ s_rresp [1:0] $end
$var wire 32 % s_rdata [31:0] $end
$var wire 1 & s_bvalid $end
$var wire 2 ' s_bresp [1:0] $end
$var wire 1 ( s_awready $end
$var wire 1 ) s_arready $end
$var reg 1 * clk $end
$var reg 1 + rst_n $end
$var reg 32 , rval [31:0] $end
$var reg 32 - s_araddr [31:0] $end
$var reg 1 . s_arvalid $end
$var reg 32 / s_awaddr [31:0] $end
$var reg 1 0 s_awvalid $end
$var reg 1 1 s_bready $end
$var reg 1 2 s_rready $end
$var reg 32 3 s_wdata [31:0] $end
$var reg 4 4 s_wstrb [3:0] $end
$var reg 1 5 s_wvalid $end
$var reg 1 6 spike_fired $end
$var integer 32 7 i [31:0] $end
$var integer 32 8 pass_count [31:0] $end
$scope module dut $end
$var wire 1 * clk $end
$var wire 1 + rst_n $end
$var wire 32 9 s_araddr [31:0] $end
$var wire 1 . s_arvalid $end
$var wire 32 : s_awaddr [31:0] $end
$var wire 1 0 s_awvalid $end
$var wire 1 1 s_bready $end
$var wire 1 2 s_rready $end
$var wire 32 ; s_wdata [31:0] $end
$var wire 4 < s_wstrb [3:0] $end
$var wire 1 5 s_wvalid $end
$var wire 16 = weight_wire [15:0] $end
$var wire 16 > threshold_wire [15:0] $end
$var wire 1 ? spike_out_wire $end
$var wire 1 @ spike_in_wire $end
$var wire 1 " s_wready $end
$var wire 1 # s_rvalid $end
$var wire 2 A s_rresp [1:0] $end
$var wire 32 B s_rdata [31:0] $end
$var wire 1 & s_bvalid $end
$var wire 2 C s_bresp [1:0] $end
$var wire 1 ( s_awready $end
$var wire 1 ) s_arready $end
$var wire 16 D membrane_wire [15:0] $end
$var wire 16 E leak_wire [15:0] $end
$scope module u_compute_core $end
$var wire 1 * clk $end
$var wire 1 + rst_n $end
$var wire 16 F weight [15:0] $end
$var wire 16 G threshold [15:0] $end
$var wire 1 @ spike_in $end
$var wire 16 H leak_factor [15:0] $end
$var reg 32 I leaked [31:0] $end
$var reg 16 J membrane [15:0] $end
$var reg 32 K next_membrane [31:0] $end
$var reg 1 ? spike_out $end
$upscope $end
$scope module u_interface $end
$var wire 1 * clk $end
$var wire 16 L leak_out [15:0] $end
$var wire 16 M membrane_in [15:0] $end
$var wire 1 + rst_n $end
$var wire 32 N s_araddr [31:0] $end
$var wire 1 . s_arvalid $end
$var wire 32 O s_awaddr [31:0] $end
$var wire 1 0 s_awvalid $end
$var wire 1 1 s_bready $end
$var wire 1 2 s_rready $end
$var wire 32 P s_wdata [31:0] $end
$var wire 4 Q s_wstrb [3:0] $end
$var wire 1 5 s_wvalid $end
$var wire 1 @ spike_in_out $end
$var wire 1 ? spike_out_in $end
$var wire 16 R threshold_out [15:0] $end
$var wire 16 S weight_out [15:0] $end
$var wire 1 " s_wready $end
$var wire 1 ( s_awready $end
$var wire 1 ) s_arready $end
$var parameter 32 T ADDR_LEAK $end
$var parameter 32 U ADDR_MEMBRANE $end
$var parameter 32 V ADDR_SPIKE_IN $end
$var parameter 32 W ADDR_SPIKE_OUT $end
$var parameter 32 X ADDR_THRESHOLD $end
$var parameter 32 Y ADDR_WEIGHT $end
$var reg 1 Z aw_active $end
$var reg 32 [ aw_addr_lat [31:0] $end
$var reg 16 \ reg_leak [15:0] $end
$var reg 1 ] reg_spike_in $end
$var reg 16 ^ reg_threshold [15:0] $end
$var reg 16 _ reg_weight [15:0] $end
$var reg 2 ` s_bresp [1:0] $end
$var reg 1 & s_bvalid $end
$var reg 32 a s_rdata [31:0] $end
$var reg 2 b s_rresp [1:0] $end
$var reg 1 # s_rvalid $end
$var reg 1 c w_active $end
$var reg 32 d w_data_lat [31:0] $end
$var reg 4 e w_strb_lat [3:0] $end
$upscope $end
$upscope $end
$scope task axi_read $end
$upscope $end
$scope task axi_write $end
$upscope $end
$upscope $end
$enddefinitions $end
$comment Show the parameter values. $end
$dumpall
b0 Y
b100 X
b10100 W
b10000 V
b1100 U
b1000 T
$end
#0
$dumpvars
bx e
bx d
xc
bx b
bx a
bx `
bx _
bx ^
x]
bx \
bx [
xZ
bx S
bx R
bx Q
bx P
bx O
bx N
bx M
bx L
bx K
bx J
bx I
bx H
bx G
bx F
bx E
bx D
bx C
bx B
bx A
x@
x?
bx >
bx =
bx <
bx ;
bx :
bx 9
b0 8
bx 7
06
05
bx 4
bx 3
02
01
00
bx /
0.
bx -
bx ,
0+
0*
x)
x(
bx '
x&
bx %
bx $
x#
x"
x!
$end
#5000
b0 K
b0 I
b0 [
1(
0Z
b0 e
b0 d
1"
0c
0@
0]
b111111010111000 E
b111111010111000 H
b111111010111000 L
b111111010111000 \
b100000000000 >
b100000000000 G
b100000000000 R
b100000000000 ^
b100000000 =
b100000000 F
b100000000 S
b100000000 _
b0 '
b0 C
b0 `
0&
b0 $
b0 A
b0 b
b0 %
b0 B
b0 a
1)
0#
0!
0?
b0 D
b0 J
b0 M
1*
#10000
0*
#15000
1*
#20000
0*
#25000
1*
#30000
0*
#35000
1*
#40000
0*
#45000
1*
#46000
1+
#50000
0*
#55000
1*
#60000
0*
#65000
1*
#70000
0*
#75000
1*
#76000
11
b1111 4
b1111 <
b1111 Q
b100000000 3
b100000000 ;
b100000000 P
15
b0 /
b0 :
b0 O
10
#80000
0*
#85000
0(
1Z
0"
1c
b1111 e
b100000000 d
1*
#90000
0*
#95000
1&
1*
#100000
0*
#105000
1(
0Z
1"
0c
0&
1*
#110000
0*
#115000
0"
1c
0(
1Z
1*
#116000
05
00
#120000
0*
#125000
1&
1*
#130000
0*
#135000
0&
1"
0c
1(
0Z
1*
#136000
01
#140000
0*
#145000
1*
#150000
0*
#155000
1*
#156000
11
b1000000000 3
b1000000000 ;
b1000000000 P
15
b100 /
b100 :
b100 O
10
#160000
0*
#165000
0(
1Z
b100 [
0"
1c
b1000000000 d
1*
#170000
0*
#175000
b1000000000 >
b1000000000 G
b1000000000 R
b1000000000 ^
1&
1*
#180000
0*
#185000
1(
0Z
1"
0c
0&
1*
#190000
0*
#195000
0"
1c
0(
1Z
1*
#196000
05
00
#200000
0*
#205000
1&
1*
#210000
0*
#215000
0&
1"
0c
1(
0Z
1*
#216000
01
#220000
0*
#225000
1*
#230000
0*
#235000
1*
#236000
11
b111111010111000 3
b111111010111000 ;
b111111010111000 P
15
b1000 /
b1000 :
b1000 O
10
#240000
0*
#245000
0(
1Z
b1000 [
0"
1c
b111111010111000 d
1*
#250000
0*
#255000
1&
1*
#260000
0*
#265000
1(
0Z
1"
0c
0&
1*
#270000
0*
#275000
0"
1c
0(
1Z
1*
#276000
05
00
#280000
0*
#285000
1&
1*
#290000
0*
#295000
0&
1"
0c
1(
0Z
1*
#296000
01
#300000
0*
#305000
1*
#310000
0*
#315000
1*
#316000
12
b0 -
b0 9
b0 N
1.
#320000
0*
#325000
b100000000 %
b100000000 B
b100000000 a
0)
1#
1*
#326000
0.
#327000
02
#330000
0*
#335000
1*
#336000
b1 8
b100000000 ,
#340000
0*
#345000
1*
#346000
12
b100 -
b100 9
b100 N
1.
#350000
0*
#355000
1)
0#
1*
#360000
0*
#365000
b1000000000 %
b1000000000 B
b1000000000 a
0)
1#
1*
#366000
0.
#367000
02
#370000
0*
#375000
1*
#376000
b1 7
b10 8
b1000000000 ,
#380000
0*
#385000
1*
#386000
11
b1 3
b1 ;
b1 P
15
b10000 /
b10000 :
b10000 O
10
#390000
0*
#395000
0"
1c
b1 d
0(
1Z
b10000 [
1*
#400000
0*
#405000
b100000000 K
1@
1]
1&
1*
#410000
0*
#415000
b11111101 K
b11111101 I
b100000000 D
b100000000 J
b100000000 M
0&
0@
0]
1"
0c
1(
0Z
1*
#420000
0*
#425000
b11111010 K
b11111010 I
0(
1Z
0"
1c
b11111101 D
b11111101 J
b11111101 M
1*
#426000
05
00
#430000
0*
#435000
b111110111 K
b11110111 I
b11111010 D
b11111010 J
b11111010 M
1@
1]
1&
1*
#440000
0*
#445000
b111110001 K
b111110001 I
1(
0Z
1"
0c
0&
0@
0]
b111110111 D
b111110111 J
b111110111 M
1*
#446000
01
#450000
0*
#455000
b111101100 K
b111101100 I
b111110001 D
b111110001 J
b111110001 M
1*
#460000
0*
#465000
b111100111 K
b111100111 I
b111101100 D
b111101100 J
b111101100 M
1*
#470000
0*
#475000
b111100010 K
b111100010 I
b111100111 D
b111100111 J
b111100111 M
1*
#480000
0*
#485000
b111011101 K
b111011101 I
b111100010 D
b111100010 J
b111100010 M
1*
#490000
0*
#495000
b111011000 K
b111011000 I
b111011101 D
b111011101 J
b111011101 M
1*
#496000
12
b1100 -
b1100 9
b1100 N
1.
#500000
0*
#505000
b111010011 K
b111010011 I
1)
0#
b111011000 D
b111011000 J
b111011000 M
1*
#510000
0*
#515000
b111001110 K
b111001110 I
b111010011 D
b111010011 J
b111010011 M
b111011000 %
b111011000 B
b111011000 a
0)
1#
1*
#516000
0.
#517000
02
#520000
0*
#525000
b111001001 K
b111001001 I
b111001110 D
b111001110 J
b111001110 M
1*
#526000
b10 7
b111011000 ,
#530000
0*
#535000
b111000100 K
b111000100 I
b111001001 D
b111001001 J
b111001001 M
1*
#536000
11
15
10
#540000
0*
#545000
b110111111 K
b110111111 I
0(
1Z
0"
1c
b111000100 D
b111000100 J
b111000100 M
1*
#550000
0*
#555000
b1010111010 K
b110111010 I
b110111111 D
b110111111 J
b110111111 M
1@
1]
1&
1*
#560000
0*
#565000
b0 K
b0 I
1(
0Z
1"
0c
0&
0@
0]
b0 D
b0 J
b0 M
1!
1?
1*
#570000
0*
#575000
16
0!
0?
0"
1c
0(
1Z
1*
#576000
05
00
#580000
0*
#585000
b100000000 K
1@
1]
1&
1*
#590000
0*
#595000
b11111101 K
b11111101 I
b100000000 D
b100000000 J
b100000000 M
0&
0@
0]
1"
0c
1(
0Z
1*
#596000
01
#600000
0*
#605000
b11111010 K
b11111010 I
b11111101 D
b11111101 J
b11111101 M
1*
#610000
0*
#615000
b11110111 K
b11110111 I
b11111010 D
b11111010 J
b11111010 M
1*
#620000
0*
#625000
b11110100 K
b11110100 I
b11110111 D
b11110111 J
b11110111 M
1*
#630000
0*
#635000
b11110001 K
b11110001 I
b11110100 D
b11110100 J
b11110100 M
1*
#640000
0*
#645000
b11101110 K
b11101110 I
b11110001 D
b11110001 J
b11110001 M
1*
#646000
12
1.
#650000
0*
#655000
b11101011 K
b11101011 I
b11101110 D
b11101110 J
b11101110 M
1)
0#
1*
#660000
0*
#665000
b11101000 K
b11101000 I
b11101110 %
b11101110 B
b11101110 a
0)
1#
b11101011 D
b11101011 J
b11101011 M
1*
#666000
0.
#667000
02
#670000
0*
#675000
b11100101 K
b11100101 I
b11101000 D
b11101000 J
b11101000 M
1*
#676000
b11 7
b11101110 ,
#680000
0*
#685000
b11100010 K
b11100010 I
b11100101 D
b11100101 J
b11100101 M
1*
#686000
11
15
10
#690000
0*
#695000
b11011111 K
b11011111 I
b11100010 D
b11100010 J
b11100010 M
0"
1c
0(
1Z
1*
#700000
0*
#705000
b111011100 K
b11011100 I
1@
1]
1&
b11011111 D
b11011111 J
b11011111 M
1*
#710000
0*
#715000
b111010111 K
b111010111 I
b111011100 D
b111011100 J
b111011100 M
0&
0@
0]
1"
0c
1(
0Z
1*
#720000
0*
#725000
b111010010 K
b111010010 I
0(
1Z
0"
1c
b111010111 D
b111010111 J
b111010111 M
1*
#726000
05
00
#730000
0*
#735000
b1011001101 K
b111001101 I
b111010010 D
b111010010 J
b111010010 M
1@
1]
1&
1*
#740000
0*
#745000
b0 K
b0 I
1(
0Z
1"
0c
0&
0@
0]
b0 D
b0 J
b0 M
1!
1?
1*
#746000
01
#750000
0*
#755000
0!
0?
1*
#760000
0*
#765000
1*
#770000
0*
#775000
1*
#780000
0*
#785000
1*
#790000
0*
#795000
1*
#796000
12
1.
#800000
0*
#805000
1)
0#
1*
#810000
0*
#815000
b0 %
b0 B
b0 a
0)
1#
1*
#816000
0.
#817000
02
#820000
0*
#825000
1*
#826000
b100 7
b0 ,
#830000
0*
#835000
1*
#836000
11
15
10
#840000
0*
#845000
0(
1Z
0"
1c
1*
#850000
0*
#855000
b100000000 K
1@
1]
1&
1*
#860000
0*
#865000
b11111101 K
b11111101 I
1(
0Z
1"
0c
0&
0@
0]
b100000000 D
b100000000 J
b100000000 M
1*
#870000
0*
#875000
b11111010 K
b11111010 I
b11111101 D
b11111101 J
b11111101 M
0"
1c
0(
1Z
1*
#876000
05
00
#880000
0*
#885000
b111110111 K
b11110111 I
1@
1]
1&
b11111010 D
b11111010 J
b11111010 M
1*
#890000
0*
#895000
b111110001 K
b111110001 I
b111110111 D
b111110111 J
b111110111 M
0&
0@
0]
1"
0c
1(
0Z
1*
#896000
01
#900000
0*
#905000
b111101100 K
b111101100 I
b111110001 D
b111110001 J
b111110001 M
1*
#910000
0*
#915000
b111100111 K
b111100111 I
b111101100 D
b111101100 J
b111101100 M
1*
#920000
0*
#925000
b111100010 K
b111100010 I
b111100111 D
b111100111 J
b111100111 M
1*
#930000
0*
#935000
b111011101 K
b111011101 I
b111100010 D
b111100010 J
b111100010 M
1*
#940000
0*
#945000
b111011000 K
b111011000 I
b111011101 D
b111011101 J
b111011101 M
1*
#946000
12
1.
#950000
0*
#955000
b111010011 K
b111010011 I
b111011000 D
b111011000 J
b111011000 M
1)
0#
1*
#960000
0*
#965000
b111001110 K
b111001110 I
b111011000 %
b111011000 B
b111011000 a
0)
1#
b111010011 D
b111010011 J
b111010011 M
1*
#966000
0.
#967000
02
#970000
0*
#975000
b111001001 K
b111001001 I
b111001110 D
b111001110 J
b111001110 M
1*
#976000
b11 8
b101 7
b111011000 ,
#980000
0*
#985000
b111000100 K
b111000100 I
b111001001 D
b111001001 J
b111001001 M
1*
#986000
12
1.
#990000
0*
#995000
b110111111 K
b110111111 I
b111000100 D
b111000100 J
b111000100 M
1)
0#
1*
#1000000
0*
#1005000
b110111010 K
b110111010 I
b111000100 %
b111000100 B
b111000100 a
0)
1#
b110111111 D
b110111111 J
b110111111 M
1*
#1006000
0.
#1007000
02
#1010000
0*
#1015000
b110110101 K
b110110101 I
b110111010 D
b110111010 J
b110111010 M
1*
#1016000
b100 8
b111000100 ,
#1020000
0*
#1025000
b110110000 K
b110110000 I
b110110101 D
b110110101 J
b110110101 M
1*
#1030000
0*
#1035000
b110101011 K
b110101011 I
b110110000 D
b110110000 J
b110110000 M
1*
#1040000
0*
#1045000
b110100110 K
b110100110 I
b110101011 D
b110101011 J
b110101011 M
1*
#1050000
0*
#1055000
b110100001 K
b110100001 I
b110100110 D
b110100110 J
b110100110 M
1*
#1060000
0*
#1065000
b110011100 K
b110011100 I
b110100001 D
b110100001 J
b110100001 M
1*
