codefest/cf06/hdl/crossbar_mac.sv
// crossbar_mac.sv
// 4x4 Binary-Weight Crossbar MAC Unit
// LLM-assisted generation (Claude, May 2026)
// out[j] = sum_i( weight[i][j] * in[i] )

module crossbar_mac (
    input  logic        clk,
    input  logic        rst_n,
    input  logic        load_en,
    input  logic [1:0]  load_row,
    input  logic [1:0]  load_col,
    input  logic        load_val,
    input  logic signed [7:0] in_vec [0:3],
    input  logic        compute_en,
    output wire signed [10:0] out [0:3]
);
    logic [15:0] weight;
    logic [3:0]  idx;
    assign idx = {load_row, load_col};

    always_ff @(posedge clk) begin
        if (!rst_n) weight <= 16'b0;
        else if (load_en) begin
            case (idx)
                4'h0: weight[0]  <= load_val;  4'h1: weight[1]  <= load_val;
                4'h2: weight[2]  <= load_val;  4'h3: weight[3]  <= load_val;
                4'h4: weight[4]  <= load_val;  4'h5: weight[5]  <= load_val;
                4'h6: weight[6]  <= load_val;  4'h7: weight[7]  <= load_val;
                4'h8: weight[8]  <= load_val;  4'h9: weight[9]  <= load_val;
                4'ha: weight[10] <= load_val;  4'hb: weight[11] <= load_val;
                4'hc: weight[12] <= load_val;  4'hd: weight[13] <= load_val;
                4'he: weight[14] <= load_val;  4'hf: weight[15] <= load_val;
            endcase
        end
    end

    assign out[0] = compute_en ? (
        (weight[0] ? $signed({{3{in_vec[0][7]}},in_vec[0]}) : -$signed({{3{in_vec[0][7]}},in_vec[0]}))
      + (weight[4] ? $signed({{3{in_vec[1][7]}},in_vec[1]}) : -$signed({{3{in_vec[1][7]}},in_vec[1]}))
      + (weight[8] ? $signed({{3{in_vec[2][7]}},in_vec[2]}) : -$signed({{3{in_vec[2][7]}},in_vec[2]}))
      + (weight[12]? $signed({{3{in_vec[3][7]}},in_vec[3]}) : -$signed({{3{in_vec[3][7]}},in_vec[3]}))
    ) : 11'bx;
    assign out[1] = compute_en ? (
        (weight[1] ? $signed({{3{in_vec[0][7]}},in_vec[0]}) : -$signed({{3{in_vec[0][7]}},in_vec[0]}))
      + (weight[5] ? $signed({{3{in_vec[1][7]}},in_vec[1]}) : -$signed({{3{in_vec[1][7]}},in_vec[1]}))
      + (weight[9] ? $signed({{3{in_vec[2][7]}},in_vec[2]}) : -$signed({{3{in_vec[2][7]}},in_vec[2]}))
      + (weight[13]? $signed({{3{in_vec[3][7]}},in_vec[3]}) : -$signed({{3{in_vec[3][7]}},in_vec[3]}))
    ) : 11'bx;
    assign out[2] = compute_en ? (
        (weight[2] ? $signed({{3{in_vec[0][7]}},in_vec[0]}) : -$signed({{3{in_vec[0][7]}},in_vec[0]}))
      + (weight[6] ? $signed({{3{in_vec[1][7]}},in_vec[1]}) : -$signed({{3{in_vec[1][7]}},in_vec[1]}))
      + (weight[10]? $signed({{3{in_vec[2][7]}},in_vec[2]}) : -$signed({{3{in_vec[2][7]}},in_vec[2]}))
      + (weight[14]? $signed({{3{in_vec[3][7]}},in_vec[3]}) : -$signed({{3{in_vec[3][7]}},in_vec[3]}))
    ) : 11'bx;
    assign out[3] = compute_en ? (
        (weight[3] ? $signed({{3{in_vec[0][7]}},in_vec[0]}) : -$signed({{3{in_vec[0][7]}},in_vec[0]}))
      + (weight[7] ? $signed({{3{in_vec[1][7]}},in_vec[1]}) : -$signed({{3{in_vec[1][7]}},in_vec[1]}))
      + (weight[11]? $signed({{3{in_vec[2][7]}},in_vec[2]}) : -$signed({{3{in_vec[2][7]}},in_vec[2]}))
      + (weight[15]? $signed({{3{in_vec[3][7]}},in_vec[3]}) : -$signed({{3{in_vec[3][7]}},in_vec[3]}))
    ) : 11'bx;
endmodule

codefest/cf06/hdl/crossbar_tb.sv
`timescale 1ns/1ps
module crossbar_tb;
    logic clk, rst_n, load_en, compute_en;
    logic [1:0] load_row, load_col;
    logic load_val;
    logic signed [7:0] in_vec [0:3];
    wire  signed [10:0] out [0:3];
    crossbar_mac dut (.*);
    initial clk = 0;
    always #5 clk = ~clk;
    initial begin
        $dumpfile("crossbar_tb.vcd");
        $dumpvars(0, crossbar_tb);
        rst_n=0; load_en=0; compute_en=0;
        load_row=0; load_col=0; load_val=0;
        in_vec[0]=10; in_vec[1]=20; in_vec[2]=30; in_vec[3]=40;
        repeat(5) @(posedge clk);
        rst_n=1;
        repeat(2) @(posedge clk);
        @(negedge clk); load_en=1; load_row=0; load_col=0; load_val=1;
        @(negedge clk); load_row=0; load_col=1; load_val=0;
        @(negedge clk); load_row=0; load_col=2; load_val=1;
        @(negedge clk); load_row=0; load_col=3; load_val=0;
        @(negedge clk); load_row=1; load_col=0; load_val=1;
        @(negedge clk); load_row=1; load_col=1; load_val=1;
        @(negedge clk); load_row=1; load_col=2; load_val=0;
        @(negedge clk); load_row=1; load_col=3; load_val=0;
        @(negedge clk); load_row=2; load_col=0; load_val=0;
        @(negedge clk); load_row=2; load_col=1; load_val=1;
        @(negedge clk); load_row=2; load_col=2; load_val=1;
        @(negedge clk); load_row=2; load_col=3; load_val=0;
        @(negedge clk); load_row=3; load_col=0; load_val=0;
        @(negedge clk); load_row=3; load_col=1; load_val=0;
        @(negedge clk); load_row=3; load_col=2; load_val=0;
        @(negedge clk); load_row=3; load_col=3; load_val=1;
        @(negedge clk); load_en=0;
        repeat(3) @(posedge clk);
        compute_en=1;
        #1;
        $display("=== Simulation Results ===");
        $display("out[0] = %0d  (expected -40)", $signed(out[0]));
        $display("out[1] = %0d  (expected   0)", $signed(out[1]));
        $display("out[2] = %0d  (expected -20)", $signed(out[2]));
        $display("out[3] = %0d  (expected -20)", $signed(out[3]));
        if ($signed(out[0])===-40 && $signed(out[1])===0 && $signed(out[2])===-20 && $signed(out[3])===-20)
            $display("=== All outputs matched! PASS ===");
        else
            $display("=== MISMATCH DETECTED ===");
        $finish;
    end
endmodule

codefest/cf06/hdl/crossbar_tb.vcd
$date
	Sun May 10 14:59:34 2026
$end
$version
	Icarus Verilog
$end
$timescale
	1ps
$end
$scope module crossbar_tb $end
$var reg 1 ! clk $end
$var reg 1 " compute_en $end
$var reg 2 # load_col [1:0] $end
$var reg 1 $ load_en $end
$var reg 2 % load_row [1:0] $end
$var reg 1 & load_val $end
$var reg 1 ' rst_n $end
$scope module dut $end
$var wire 1 ! clk $end
$var wire 1 " compute_en $end
$var wire 2 ( load_col [1:0] $end
$var wire 1 $ load_en $end
$var wire 2 ) load_row [1:0] $end
$var wire 1 & load_val $end
$var wire 1 ' rst_n $end
$var wire 4 * idx [3:0] $end
$var reg 16 + weight [15:0] $end
$upscope $end
$upscope $end
$enddefinitions $end
$comment Show the parameter values. $end
$dumpall
$end
#0
$dumpvars
bx +
b0 *
b0 )
b0 (
0'
0&
b0 %
0$
b0 #
0"
0!
$end
#5000
b0 +
1!
#10000
0!
#15000
1!
#20000
0!
#25000
1!
#30000
0!
#35000
1!
#40000
0!
#45000
1'
1!
#50000
0!
#55000
1!
#60000
0!
#65000
1!
#70000
1&
1$
0!
#75000
b1 +
1!
#80000
0&
b1 *
b1 #
b1 (
0!
#85000
1!
#90000
1&
b10 *
b10 #
b10 (
0!
#95000
b101 +
1!
#100000
0&
b11 *
b11 #
b11 (
0!
#105000
1!
#110000
1&
b0 #
b0 (
b100 *
b1 %
b1 )
0!
#115000
b10101 +
1!
#120000
b101 *
b1 #
b1 (
0!
#125000
b110101 +
1!
#130000
0&
b110 *
b10 #
b10 (
0!
#135000
1!
#140000
b111 *
b11 #
b11 (
0!
#145000
1!
#150000
b0 #
b0 (
b1000 *
b10 %
b10 )
0!
#155000
1!
#160000
1&
b1001 *
b1 #
b1 (
0!
#165000
b1000110101 +
1!
#170000
b1010 *
b10 #
b10 (
0!
#175000
b11000110101 +
1!
#180000
0&
b1011 *
b11 #
b11 (
0!
#185000
1!
#190000
b0 #
b0 (
b1100 *
b11 %
b11 )
0!
#195000
1!
#200000
b1101 *
b1 #
b1 (
0!
#205000
1!
#210000
b1110 *
b10 #
b10 (
0!
#215000
1!
#220000
1&
b1111 *
b11 #
b11 (
0!
#225000
b1000011000110101 +
1!
#230000
0$
0!
#235000
1!
#240000
0!
#245000
1!
#250000
0!
#255000
1"
1!
